<?xml version="1.0" encoding="UTF-8" standalone="no"?>
<catalog prefer="public" xmlns="urn:oasis:names:tc:entity:xmlns:xml:catalog">
    <group id="Folder Repository, directory=, recursive=true, Auto-Update=true, version=2" prefer="public" xml:base="">
        <uri id="Automatically generated entry, Timestamp=1530371629589" name="duplicate:http://www.w3.org/2002/07/owl" uri="123.owl"/>
        <uri id="Automatically generated entry, Timestamp=1530371629589" name="duplicate:http://www.w3.org/2002/07/owl" uri="rdf.owl"/>
        <uri id="Automatically generated entry, Timestamp=1530371629589" name="duplicate:http://www.w3.org/2002/07/owl" uri="rdf_atiso.owl"/>
        <uri id="Automatically generated entry, Timestamp=1530371629589" name="duplicate:http://www.w3.org/2002/07/owl" uri="rdf_bapcai.owl"/>
        <uri id="Automatically generated entry, Timestamp=1530371629589" name="duplicate:http://www.w3.org/2002/07/owl" uri="rdf_bido.owl"/>
        <uri id="Automatically generated entry, Timestamp=1530371629589" name="duplicate:http://www.w3.org/2002/07/owl" uri="rdf_carot.owl"/>
        <uri id="Automatically generated entry, Timestamp=1530371629589" name="duplicate:http://www.w3.org/2002/07/owl" uri="rdf_cuhanh.owl"/>
        <uri id="Automatically generated entry, Timestamp=1530371629589" name="duplicate:http://www.w3.org/2002/07/owl" uri="rdf_dualeo.owl"/>
        <uri id="Automatically generated entry, Timestamp=1530371629589" name="duplicate:http://www.w3.org/2002/07/owl" uri="rdf_luong.owl"/>
        <uri id="Automatically generated entry, Timestamp=1530371629589" name="duplicate:http://www.w3.org/2002/07/owl" uri="rdf_luong_loi.owl"/>
        <uri id="Automatically generated entry, Timestamp=1530371629589" name="duplicate:http://www.w3.org/2002/07/owl" uri="rdf_luong_thit_vit.owl"/>
        <uri id="Automatically generated entry, Timestamp=1530371629589" name="duplicate:http://www.w3.org/2002/07/owl" uri="rdf_lộc.owl"/>
        <uri id="Automatically generated entry, Timestamp=1530371629589" name="duplicate:http://www.w3.org/2002/07/owl" uri="rdf_nho.owl"/>
        <uri id="Automatically generated entry, Timestamp=1530371629589" name="duplicate:http://www.w3.org/2002/07/owl" uri="rdf_salad.owl"/>
        <uri id="Automatically generated entry, Timestamp=1530371629589" name="duplicate:http://www.w3.org/2002/07/owl" uri="rdf_testing.owl"/>
    </group>
</catalog>
